contentai_activity_classifier/__init__.py
contentai_activity_classifier/_version.py
contentai_activity_classifier/data_loader.py
contentai_activity_classifier/features.py
contentai_activity_classifier/main.py
contentai_activity_classifier/modeling.py
contentai_activity_classifier/multiclass.py
contentai_activity_classifier/nine_layers.py
contentai_activity_classifier/wrapped.py
contentai_activity_classifier-1.3.7.dist-info/LICENSE
contentai_activity_classifier-1.3.7.dist-info/METADATA
contentai_activity_classifier-1.3.7.dist-info/WHEEL
contentai_activity_classifier-1.3.7.dist-info/entry_points.txt
contentai_activity_classifier-1.3.7.dist-info/top_level.txt
contentai_activity_classifier-1.3.7.dist-info/RECORD
