Metadata-Version: 2.1
Name: contentai-activity-classifier
Version: 1.3.7
Summary: ContentAI Activity Classification Service
Home-page: https://gitlab.research.att.com/turnercode/activity-classifier-extractor
Author: Eric Zavesky
License: Apache
Platform: UNKNOWN
Requires-Python: >=3.6
Requires-Dist: pandas (==1.0.4)
Requires-Dist: numexpr (==2.7.1)
Requires-Dist: scikit-learn (==0.23.1)
Requires-Dist: h5py (==2.10.0)
Requires-Dist: matplotlib (==3.2.1)
Requires-Dist: imblearn (==0.0)
Requires-Dist: tensorflow (==2.2.0)
Requires-Dist: contentaiextractor (>=1.0.4)
